pyrig/__init__.py
pyrig/dev/__init__.py
pyrig/dev/builders/__init__.py
pyrig/dev/builders/base/__init__.py
pyrig/dev/builders/base/base.py
pyrig/dev/builders/pyinstaller.py
pyrig/dev/cli/__init__.py
pyrig/dev/cli/cli.py
pyrig/dev/cli/commands/__init__.py
pyrig/dev/cli/commands/build_artifacts.py
pyrig/dev/cli/commands/create_root.py
pyrig/dev/cli/commands/create_tests.py
pyrig/dev/cli/commands/init_project.py
pyrig/dev/cli/commands/make_inits.py
pyrig/dev/cli/commands/protect_repo.py
pyrig/dev/cli/shared_subcommands.py
pyrig/dev/cli/subcommands.py
pyrig/dev/configs/__init__.py
pyrig/dev/configs/base/__init__.py
pyrig/dev/configs/base/badges_md.py
pyrig/dev/configs/base/base.py
pyrig/dev/configs/base/copy_module.py
pyrig/dev/configs/base/copy_module_docstr.py
pyrig/dev/configs/base/dict_cf.py
pyrig/dev/configs/base/init.py
pyrig/dev/configs/base/json.py
pyrig/dev/configs/base/list_cf.py
pyrig/dev/configs/base/markdown.py
pyrig/dev/configs/base/py_package.py
pyrig/dev/configs/base/py_tests.py
pyrig/dev/configs/base/python.py
pyrig/dev/configs/base/string_.py
pyrig/dev/configs/base/toml.py
pyrig/dev/configs/base/txt.py
pyrig/dev/configs/base/typed.py
pyrig/dev/configs/base/workflow.py
pyrig/dev/configs/base/yaml.py
pyrig/dev/configs/base/yml.py
pyrig/dev/configs/containers/__init__.py
pyrig/dev/configs/containers/container_file.py
pyrig/dev/configs/docs/__init__.py
pyrig/dev/configs/docs/mkdocs.py
pyrig/dev/configs/dot_env.py
pyrig/dev/configs/dot_python_version.py
pyrig/dev/configs/git/__init__.py
pyrig/dev/configs/git/branch_protection.py
pyrig/dev/configs/git/gitignore.py
pyrig/dev/configs/git/pre_commit.py
pyrig/dev/configs/licence.py
pyrig/dev/configs/markdown/__init__.py
pyrig/dev/configs/markdown/docs/__init__.py
pyrig/dev/configs/markdown/docs/api.py
pyrig/dev/configs/markdown/docs/index.py
pyrig/dev/configs/markdown/readme.py
pyrig/dev/configs/py_typed.py
pyrig/dev/configs/pyproject.py
pyrig/dev/configs/pyrig/__init__.py
pyrig/dev/configs/pyrig/pyproject.py
pyrig-4.2.21.dist-info/licenses/LICENSE
pyrig-4.2.21.dist-info/WHEEL
pyrig-4.2.21.dist-info/entry_points.txt
pyrig-4.2.21.dist-info/METADATA
pyrig-4.2.21.dist-info/RECORD
