Metadata-Version: 2.4
Name: pyrig
Version: 4.2.21
Summary: A Python toolkit to rig up your project that standardizes and automates project setup, configuration and development.
Keywords: project-setup,automation,scaffolding,cli,testing,ci-cd,devops,packaging
Author: Winipedia
License-Expression: MIT
License-File: LICENSE
Classifier: Development Status :: 5 - Production/Stable
Classifier: Intended Audience :: Developers
Classifier: Topic :: Software Development :: Build Tools
Classifier: Topic :: Software Development :: Libraries :: Python Modules
Classifier: Topic :: Software Development :: Quality Assurance
Classifier: Topic :: Software Development :: Testing
Classifier: Topic :: System :: Installation/Setup
Classifier: Topic :: System :: Software Distribution
Classifier: Programming Language :: Python :: 3.12
Classifier: Programming Language :: Python :: 3.13
Classifier: Programming Language :: Python :: 3.14
Classifier: Operating System :: OS Independent
Classifier: Typing :: Typed
Requires-Dist: typer>=0.20.0
Maintainer: Winipedia
Requires-Python: >=3.12
Project-URL: Changelog, https://github.com/Winipedia/pyrig/releases
Project-URL: Documentation, https://Winipedia.github.io/pyrig
Project-URL: Homepage, https://github.com/Winipedia/pyrig
Project-URL: Issues, https://github.com/Winipedia/pyrig/issues
Project-URL: Source, https://github.com/Winipedia/pyrig
